ngpu/__init__.py
ngpu/core/__init__.py
ngpu/core/export.py
ngpu/core/index.py
ngpu/core/loader.py
ngpu/core/search.py
ngpu/data/states-and-lgas-and-wards-and-polling-units.json
ngpu/data/states-and-lgas-and-wards.json
ngpu/data/states-and-lgas.json
ngpu/data/states.json
ngpu/ml/__init__.py
ngpu/ml/diagnostics.py
ngpu/ml/encoder.py
ngpu/ml/hierarchy_features.py
ngpu-0.1.0.dist-info/licenses/LICENSE
ngpu-0.1.0.dist-info/METADATA
ngpu-0.1.0.dist-info/WHEEL
ngpu-0.1.0.dist-info/top_level.txt
ngpu-0.1.0.dist-info/RECORD
