Metadata-Version: 2.4
Name: ngpu
Version: 0.1.0
Summary: Hierarchical polling unit intelligence for Nigeria (ML-ready)
Author-email: "Chidiebere V. Christopher" <vchidiebere.vc@gmail.com>, MaryBlessing Umeh <umaryblessing@gmail.com>
Project-URL: Homepage, https://github.com/93Chidiebere/ngpu
Project-URL: Issues, https://github.com/93Chidiebere/ngpu/issues
Requires-Python: >=3.9
License-File: LICENSE
Requires-Dist: pandas>=1.5
Requires-Dist: scikit-learn>=1.2
Requires-Dist: rapidfuzz>=3.0
Dynamic: license-file
